{
  "$schema": "https://developer.microsoft.com/json-schemas/fabric/item/report/definition/visualContainer/2.1.0/schema.json",
  "name": "8f767e15a0519906cd4c",
  "position": {
    "x": 10.256410256410255,
    "y": 430.70175438596493,
    "z": 2000,
    "height": 172.28070175438597,
    "width": 379.48717948717945,
    "tabOrder": 1000
  },
  "visual": {
    "visualType": "columnChart",
    "query": {
      "queryState": {
        "Category": {
          "projections": [
            {
              "field": {
                "Column": {
                  "Expression": {
                    "SourceRef": {
                      "Entity": "dim_client"
                    }
                  },
                  "Property": "Age Bins"
                }
              },
              "queryRef": "dim_client.Age Bins",
              "nativeQueryRef": "Age Bins",
              "active": true
            }
          ]
        },
        "Y": {
          "projections": [
            {
              "field": {
                "Measure": {
                  "Expression": {
                    "SourceRef": {
                      "Entity": "fact_records"
                    }
                  },
                  "Property": "Default Rate"
                }
              },
              "queryRef": "fact_records.Default Rate",
              "nativeQueryRef": "Default Rate"
            }
          ]
        }
      },
      "sortDefinition": {
        "sort": [
          {
            "field": {
              "Measure": {
                "Expression": {
                  "SourceRef": {
                    "Entity": "fact_records"
                  }
                },
                "Property": "Default Rate"
              }
            },
            "direction": "Descending"
          }
        ],
        "isDefaultSort": true
      }
    },
    "objects": {
      "valueAxis": [
        {
          "properties": {
            "showAxisTitle": {
              "expr": {
                "Literal": {
                  "Value": "false"
                }
              }
            }
          }
        }
      ],
      "categoryAxis": [
        {
          "properties": {
            "showAxisTitle": {
              "expr": {
                "Literal": {
                  "Value": "false"
                }
              }
            }
          }
        }
      ]
    },
    "visualContainerObjects": {
      "title": [
        {
          "properties": {
            "text": {
              "expr": {
                "Literal": {
                  "Value": "'Default Rate'"
                }
              }
            },
            "fontFamily": {
              "expr": {
                "Literal": {
                  "Value": "'''Segoe UI Semibold'', wf_segoe-ui_semibold, helvetica, arial, sans-serif'"
                }
              }
            }
          }
        }
      ]
    },
    "drillFilterOtherVisuals": true
  },
  "parentGroupName": "c414427061efd828cabf"
}